summershum
