Metadata-Version: 1.0
Name: summershum
Version: 0.1.4
Summary: fedmsg consumer that extracts hashes of source files
Home-page: https://github.com/fedora-infra/summershum
Author: Pierre-Yves Chibon & Ralph Bean
Author-email: admin@fedoraproject.org
License: gplv2+
Platform: UNKNOWN
